easy_binary_file/__init__.py
easy_binary_file/easy_binary_file.py
easy_binary_file-1.0.4.dist-info/LICENSE
easy_binary_file-1.0.4.dist-info/METADATA
easy_binary_file-1.0.4.dist-info/WHEEL
easy_binary_file-1.0.4.dist-info/top_level.txt
easy_binary_file-1.0.4.dist-info/RECORD
