Metadata-Version: 2.1
Name: easy-binary-file
Version: 1.0.4
Summary: Easy way to use binary files with built in class and functions
Home-page: https://github.com/Invarato/easy_binary_file_project
Author: Ramon Invarato Menendez
Author-email: r.invarato@gmail.com
License: UNKNOWN
Platform: UNKNOWN
Classifier: Programming Language :: Python :: 3
Classifier: License :: OSI Approved :: MIT License
Classifier: Operating System :: OS Independent
Requires-Python: >=3.0
